{
    "arb": {
        "displayName": "Levantine Arabic",
        "symbols": [
            "ARB"
        ],
        "aiNote": "Ensure to actually produce Levantine Arabic as spoken in Syria, Lebanon or Palestine, not textbook MSA. Return Arabic script. If you want to include a gap in the text, use the (U+0640 TATWEEL) character"
    },
    "deu": {
        "displayName": "German",
        "symbols": [
            "DE"
        ]
    },
    "eng": {
        "displayName": "English",
        "symbols": [
            "EN"
        ]
    },
    "fin": {
        "displayName": "Finnish (Suomi)",
        "symbols": [
            "🇫🇮"
        ]
    },
    "ita": {
        "displayName": "Italian",
        "symbols": [
            "🇮🇹"
        ],
        "aiNote": "Focus on spoken, conventional Italian."
    },
    "pol": {
        "displayName": "Polish",
        "symbols": [
            "🇵🇱"
        ]
    },
    "por": {
        "displayName": "Portugese",
        "symbols": [
            "🇧🇷"
        ],
        "aiNote": "Focus on spoken, conventional Portugese. Give African and Brazilian the same weight as European Spanish."
    },
    "rus": {
        "displayName": "Russian",
        "symbols": [
            "🇷🇺"
        ]
    },
    "spa": {
        "displayName": "Spanish",
        "symbols": [
            "🇲🇽"
        ],
        "aiNote": "Focus on spoken, conventional Spanish. Give South American Spanish the same weight as European Spanish."
    }
}